magicfeedback-1.0.4.dist-info/licenses/LICENCE
magicfeedback_sdk/__init__.py
magicfeedback_sdk/auth.py
magicfeedback_sdk/client.py
magicfeedback_sdk/logging_config.py
magicfeedback_sdk/api/__init__.py
magicfeedback_sdk/api/campaigns.py
magicfeedback_sdk/api/contacts.py
magicfeedback_sdk/api/feedback.py
magicfeedback_sdk/api/integrations_questions.py
magicfeedback_sdk/api/metrics.py
magicfeedback_sdk/api/reports.py
magicfeedback_sdk/utils/__init__.py
magicfeedback_sdk/utils/request.py
magicfeedback-1.0.4.dist-info/METADATA
magicfeedback-1.0.4.dist-info/WHEEL
magicfeedback-1.0.4.dist-info/top_level.txt
magicfeedback-1.0.4.dist-info/RECORD
