Metadata-Version: 2.4
Name: MagicFeedback
Version: 1.0.4
Summary: SDK for MagicFeedback API
Home-page: https://github.com/MagicFeedback/magicfeedback_python_sdk
Author: Francisc Arias
Author-email: Francisco Arias <farias@magicfedback.io>
Project-URL: Homepage, https://github.com/MagicFeedback/magicfeedback_python_sdk
Project-URL: Issues, https://github.com/MagicFeedback/magicfeedback_python_sdk/issues
Classifier: Programming Language :: Python :: 3
Classifier: License :: OSI Approved :: MIT License
Classifier: Operating System :: OS Independent
Requires-Python: >=3.8
License-File: LICENCE
Dynamic: author
Dynamic: home-page
Dynamic: license-file
Dynamic: requires-python
